{
    "camera": {
        "blobMaxArea": 8.0,
        "blobMinArea": 0.05000000074505806,
        "enableClipping": true,
        "fillHolesOnPolygons": false,
        "floodfillHoles": false,
        "gaussianBlur": 9,
        "nConsidered": 8,
        "polygonTolerance": 1.0,
        "showPolygons": false,
        "useMask": false
    },
    "render": {
        "color": 7618646,
        "color_alpha": 85,
        "fakeTrialsVisibility": 0.0,
        "motionBlurStrength": 0.5,
        "particleGlow": 1.0,
        "showVideoPreview": true,
        "size": 3,
        "trailDecayRate": 1.0,
        "useColorVariation": true,
        "useEnhancedShaders": true,
        "useFaketrails": true,
        "useImprovedTrails": true,
        "useMotionBlur": true,
        "useShaders": true,
        "videoColor": 2339397,
        "videoColor_alpha": 40,
        "videopreviewVisibility": 0.2991071343421936
    },
    "simulation": {
        "amount": 278.6813049316406,
        "applyThermostat": true,
        "coupling": 0.8111607432365417,
        "depthFieldScale": -103303.5703125,
        "enableCollisionLogging": true,
        "radius": 24,
        "targetTemperature": 8513.392578125
    }
}